graphe/__init__.py
graphe/draw.py
graphe/digraph/__init__.py
graphe/digraph/cycle.py
graphe/digraph/ddfo.py
graphe/digraph/digraph.py
graphe/digraph/digraphdfs.py
graphe/digraph/ksscc.py
graphe/digraph/regex.py
graphe/digraph/symboldigraph.py
graphe/digraph/topological.py
graphe/graph/__init__.py
graphe/graph/bfs.py
graphe/graph/cc.py
graphe/graph/dfs.py
graphe/graph/graph.py
graphe-0.1.2.dist-info/LICENSE
graphe-0.1.2.dist-info/METADATA
graphe-0.1.2.dist-info/WHEEL
graphe-0.1.2.dist-info/top_level.txt
graphe-0.1.2.dist-info/RECORD
