Metadata-Version: 2.1
Name: graphe
Version: 0.1.2
Summary: Collection of graph algorithms, applications and visualisations
Author-email: Morten Jagd Christensen <mortenjc@jcaps.com>
Project-URL: Homepage, https://github.com/mortenjc/graphe
Project-URL: Documentation, https://graphe.readthedocs.io/en/latest/
Project-URL: Bug Tracker, https://github.com/mortenjc/graphe/issues
Classifier: Programming Language :: Python :: 3
Classifier: License :: OSI Approved :: BSD License
Classifier: Operating System :: OS Independent
Requires-Python: >=3.7
License-File: LICENSE
